{
  "Common": {
    "Saving": "正在儲存",
    "Remove": {
      "Title": "移除",
      "Confirm": "確認移除",
      "No": "否，不要移除"
    },
    "ID": "ID",
    "Add": "新增",
    "True": "真",
    "False": "偽",
    "Edit": "編輯",
    "Cancel": "取消",
    "Clear": "清除",
    "Save": "儲存",
    "Saved": "已儲存",
    "DontSave": "不儲存",
    "Enabled": "啟用",
    "Disabled": "停用",
    "Required": "必填",
    "Removed": "移除",
    "Advanced": "進階項目",
    "DisplayName": "顯示名稱",
    "DisplayURL": "顯示 URL",
    "LogoURL": "Logo URL",
    "LogoutURL": "登出 URL",
    "Callback": "回呼",
    "CallbackURL": "回呼 URL",
    "CORSUrl": "CORS URL",
    "CORS": "CORS",
    "Description": "描述",
    "ExpirationDate": "逾期日",
    "Expiration": "逾期",
    "Invalid": "無效",
    "Emphasize": "強調",
    "Back": "上一個",
    "Next": "下一個",
    "Submit": "提交",
    "Status": "狀態",
    "URL": "URL",
    "LogoutUri": "登出 Url",
    "Close": "關閉",
    "Change": "變更",
    "Logo": "Logo",
    "Info": "資訊",
    "Email": "email",
    "Phone": "電話",
    "Name": "名稱",
    "Created": "被建立",
    "Added": "新增",
    "Expires": "過期",
    "Reserved": "保留",
    "Secrets": "密錀",
    "GenerateRandom": "隨機產生一個32字元字串",
    "Restrictions": "限制使用之IdP",
    "Never": "永久",
    "OK": "OK",
    "Yes": "是",
    "No": "否",
    "Note": "註釋",
    "Signout": "登出",
    "Revoke": "撤消",
    "String": "字串",
    "Number": "數字",
    "Date": "日期",
    "Error": "錯誤",
    "Type": "類別",
    "Value": "值",
    "Button": "按鈕",
    "DatePicker": "日期選擇",
    "Boolean": "布林值",
    "Text": "文字",
    "Search": "搜尋...",
    "Authenticating": "認證中",
    "Loading": "載入中",
    "AreYouSureContinue": "您確定要繼續?",
    "CompanyName": "Rock Solid Knowledge 公司",
    "AppName": "IdentityExpress AdminUI",
    "Password": "密碼",
    "Policy": "存取原則",
    "Minute": "分",
    "Hour": "時",
    "Hours": "小時",
    "Day": "天",
    "Week": "週",
    "Month": "月",
    "Year": "日",
    "Actions": "操作",
    "Assign": "分配",
    "Unassign": "取消分配",
    "Days": "天",
    "Weeks": "星期",
    "Months": "月",
    "Years": "年",
    "Unlimited": "無限",
    "Audits": "審計",
    "Reset": "重設",
    "SaveAll": "全部儲存",
    "Custom": "自訂",
    "Or": "或",
    "RedirectUris": "重新導向URI",
    "MustBeHttpsInProduction": "以上通訊協定以上仰賴生產中的TLS",
    "Start": "開始",
    "GrantTypes": "授與類型",
    "Properties": "屬性",
    "Warning": "警告",
    "ShowMore": "顯示更多",
    "ShowLess": "顯示較少",
    "Thumbprint": "憑證指紋",
    "Subject": "主旨",
    "UntilExpiry": "天數",
    "ExpiresOn": "截止日期",
    "ExpiresIn": "Expires In",
    "CommunityPolicyNotice": "這是存取原則螢幕的預覽。在社區版中已刪除了存取原則功能。您可以使用該螢幕，但這些原則都不會生效。如需瞭解有關完整AdminUI產品的更多資訊，請按一下下面的連結",
    "SaveAndConfigure": "儲存並設定",
    "SaveAndAdd": "儲存並新增其他項目",
    "LoadingPleaseWait": "正在載入中，請稍候...",
    "AddAndAdd": "新增並新增另一個",
    "Delete": {
      "Title": "刪除",
      "TitleUndo": "復原",
      "Deleted": "刪除",
      "Confirm": "確認刪除",
      "UndoDelete": "復原",
      "ConfirmUndoDelete": "您確認要復原使用者",
      "AreYouSure": "您確定要刪除值嗎？",
      "AreYouSureSimple": "您確定要刪除",
      "AreYouSureSimple2": "您確定要刪除嗎？",
      "AreYouSureSimple3": "\"確定要刪除這個嗎？",
      "Warning": "<strong>注意:</strong> 此操作無法撤消.",
      "No": "不，不要刪除"
    },
    "Types": {
      "String": "字串",
      "Int": "整數",
      "DateTime": "日期",
      "Boolean": "布林值",
      "Name": "類別名稱",
      "Description": "類別描述"
    },
    "ResetPassword": {
      "Confirm": "確認重置",
      "AreYouSureSimple": "你確定要重設密碼嗎",
      "Title": "重置密碼",
      "HowToSetupTitle": "設定使用者密碼重置Webhook",
      "HowToSetup": "密碼重設Webhook在使用前需先設定。進階資訊，請參閱AdminUI Webhook文件。"
    },
    "UserEditable": "使用者可編輯",
    "Key": "關鍵值",
    "CommunityEditionBanner": "歡迎使用AdminUI社群版。 這是用於管理IdentityServer組態和用戶的AdminUI工具的免費版本。它僅限於10個使用者和2個用戶端。 要了解有關完整AdminUI產品的更多訊息，請點擊下面的連結"
  },
  "Nav": {
    "Breadcrumbs": "階層連結",
    "Active": "使用中",
    "Account": "帳戶",
    "Found": "找到",
    "ResultsFound": "個結果被找到",
    "PageXofX": "第{0}頁 共{1}頁",
    "First": "第一個",
    "Previous": "上一個",
    "Next": "下一個",
    "Last": "最後一個",
    "Logout": "登出",
    "Home": "首頁",
    "Users": "使用者(User)",
    "Roles": "角色(Role)",
    "ClaimTypes": "宣告(Claim)",
    "Clients": "用戶端(Client)",
    "Resources": "資源(Resource)",
    "IdentityResources": "身份資源(Identity Resource)",
    "ProtectedResources": "應用程式介面資源(Api Resource)",
    "ToTop": "回到最上方",
    "Support": "支援",
    "MobileListInfo": "連續點擊將開啟使用者明細",
    "PerPage": "筆(每頁)",
    "Displaying": "顯示",
    "Page": "頁",
    "of": "的",
    "Details": "明細",
    "Scopes": "範圍",
    "Authentication": "認證",
    "Applications": "應用程式",
    "Additional Details": "額外的明細",
    "ToggleNavigation": "切換巡覽",
    "Login": "登入",
    "External Logins": "外部登入",
    "Settings": "設定",
    "AccessPolicy": "存取原則",
    "IdentityServer": "IdentityServer 管理",
    "UserManagement": "使用者管理",
    "Start": "開始",
    "Auditing": "正在審計",
    "Audits": "審計",
    "SkipToContent": "跳至內容",
    "Menu": "功能表",
    "SubMenu": "子功能表",
    "Claims": "宣告",
    "Secrets": "祕密",
    "Saml": "SAML",
    "WsFed": "WS-Fed"
  },
  "Errors": {
    "NotFoundTitle": "Error 404",
    "NotFoundDescription": "該頁面或資源找不到.",
    "ForbiddenTitle": "Error 403",
    "ForbiddenDescription": "您沒有權限存取此頁.",
    "UnauthenticatedTitle": "尚未認證或認證過期",
    "UnauthenticatedDescription": "即將重導至登入頁...",
    "Unauthorized": "未授權",
    "ContactAdmin": "您未被允許使用 AdminUI, 請連絡您的系統管理人員",
    "ResourceNotFound": "未找到資源(resource)",
    "ResourceNotFoundDescription": "未找到此項資源(resource)",
    "RssUnavailable": "RSS不可用",
    "ValidateImportError": {
      "ImportNull": "正在嘗試匯入 json 時發生錯誤",
      "WrongVersion": "抱歉，匯出檔案來自 AdminUI ({0}) 不相容的版本。僅支援 2.6.0 - {1}版本",
      "ValidateImport": "抱歉，正在匯入時發生問題。請再試一次"
    }
  },
  "Index": {
    "Title": "儀表板",
    "LicensedTo": "授權給",
    "LicenseType": "授權類型",
    "Users": {
      "Title": "使用者管理",
      "Body": "輕鬆管理IdentityServer使用者."
    },
    "Claims": {
      "Heading": "宣告",
      "Title": "宣告與角色管理",
      "Body": "管理用戶端和應用程式可用之宣告類型和角色"
    },
    "IdentityServer": {
      "Title": "IdentityServer 組態",
      "Body": "管理IdentityServer用戶應用程式,及用戶端與資源端應用程式介面的資源"
    }
  },
  "Users": {
    "Title": "使用者",
    "Singular": "使用者",
    "AddUser": "新增使用者",
    "NewUser": "新使用者",
    "SearchUser": "搜尋使用者...",
    "MinimumSearchLength": "最小搜尋長度為2個字元",
    "Filter": {
      "Active": "啟用",
      "Blocked": "停用",
      "Label": "僅顯示符合以下條件的使用者：",
      "Deleted": "已刪除"
    },
    "Username": "使用者名稱",
    "FullName": "全名",
    "Email": "Email 位址",
    "FirstName": "名字",
    "LastName": "姓氏",
    "Details": {
      "AdditionalDetailsBody": "設定與使用者相關的額外資訊. 若要建立新的類型,請前往宣告(Claim)類型之功能頁面.",
      "AddClaim": "新增請求"
    },
    "CopyValue": "從明細中複製值",
    "NoUsersFound": "找不到使用者",
    "AddAnother": "連續新增使用者",
    "CloseBox": "選擇 <strong>新增</strong> 將關閉此對話框，並回到使用者列表。",
    "Password": {
      "Requirements": {
        "1": "至少一個大寫字母",
        "2": "至少一個小寫字母",
        "3": "至少一位數字",
        "4": "至少一個特殊字元 (# ? ! @ $ % ^ &amp; * -)",
        "5": "至少八個字元長度"
      },
      "Title": "密碼"
    },
    "Delete": {
      "DeletedUser": "使用者已刪除.",
      "AuditingPurposes": "使用者資訊仍會保留以方便稽核",
      "Confirmation": "{0}已刪除。使用者資料仍可存取審核"
    },
    "First page of results": "第一頁",
    "Previous page of results": "前一頁",
    "Last page of results": "最末頁",
    "Next page of results": "下一頁",
    "Applications": {
      "Access": "使用者已同意或目前已擁有IdentityServer端Token的應用程式.",
      "None": "此使用者尚未與任何應用程式建立關聯",
      "Revoke": "全部撤消",
      "RevokeApp": "撤消應用程式",
      "RevokeAll": "是, 全部撤消",
      "RevokeConfirm": "請確認，此帳號上 <u>所有</u> 應用程式之存取權限即將被撤銷. <br />您亦可透過點選單一應用程式之彈出視窗來逐一撤銷.",
      "RevokeUserConfirm": "此將撤消存取權限",
      "ForUser": "給使用者",
      "RevokeYes": "是, 撤消應用程式",
      "Accessible": "應用程式可存取的資源/範圍："
    }
  },
  "UserDetails": {
    "AdditionalDetailsBlurb": "額外的資訊Blurb",
    "Active": "啟用",
    "Blocked": "停用",
    "Title": "使用者資料",
    "Assigned": "已指派項目",
    "Available": "可選擇項目",
    "Search Roles": "搜尋角色...",
    "Select Type": "選擇類別",
    "Value": "值",
    "Name": "名稱",
    "Search for apps": "搜尋apps",
    "Password": "密碼",
    "New Password": "新密碼",
    "Confirm Password": "確認密碼",
    "Two Step": "兩階段",
    "Copy Value": "從明細中複製值",
    "Phone Number": "電話號碼",
    "Email Address": "Email Address",
    "MisMatchPasswordWarning": "密碼 <u>不</u> 相符",
    "PasswordMatchMessage": " 密碼相符",
    "ChangePassword": "重置密碼",
    "UnauthorizedWarning": "您沒有指派此用戶這項宣告(Claim)之權限",
    "UnauthorizedWarningEdit": "您沒有修改此用戶這項宣告(Claim)之權限",
    "UnauthorizedWarningDelete": "您沒有移除此用戶這項宣告(Claim)之權限",
    "NoRolesFoundWarning": "找不到任何使用者角色",
    "NoClaimsMessage": "No additional details found for this user"
  },
  "UserLogins": {
    "ProviderDisplayName": "識別提供者(IdP)名稱",
    "LoginProvider": "登入提供者",
    "ProviderKey": "使用者識別",
    "NoLogins": "使用者目前尚未使用外部登入",
    "RevokeExternalLogin": "撤消外部登入",
    "RevokeLoginConfirmationText": "您確定要撤消此外部登入"
  },
  "Roles": {
    "AreYouSureRemove": "您是否確定希望將<b>{0}</b>從<b>{1}</b>移除？",
    "UpdateBadRequest": "無法處理您的要求",
    "ManageUsers": "管理使用者",
    "AddUsers": "新增使用者",
    "AddRemoveUsersFromRole": "新增使用者或將使用者從<b>{0}</b>移除",
    "User": "使用者",
    "InRole": "角色：",
    "SearchAllUsers": "搜尋所有使用者",
    "Adding": "新增",
    "Removing": "移除",
    "CancelAdding": "取消新增",
    "CancelRemoving": "取消移除",
    "NoUsersAdding": "不會新增任何使用者",
    "NoUsersRemoving": "不會移除任何使用者",
    "RoleUserManagement": "角色使用者管理",
    "AddRemoveUserFromRole": "新增使用者或將其移除出",
    "NoResults": "未找到相符的使用者",
    "NotSelected": "搜尋要新增或從此角色移除的使用者（最少2個字元）",
    "SavingPleaseWait": "正在儲存，請稍候......",
    "Role": "角色",
    "NewRole": "新增角色",
    "AddAnother": "連續新增角色",
    "AddAnotherInfo": "選擇 <strong>連續新增角色</strong> 在「新增角色」之後會保留這個對話框，您可以繼續新增另一個角色.",
    "CloseReturnsRoleList": "選擇 <strong>新增</strong> 將關閉對話框，並回到角色列表.",
    "RoleRemoved": "角色已被刪除.",
    "Search": "搜尋角色...",
    "ReservedHelp": "此角色已被保留，不可編輯",
    "Reserved": "保留",
    "NoRolesFound": "找不到角色",
    "RoleCreated": "角色已建立",
    "Success": "角色更新成功",
    "AreYouSureDelete": "您確定要刪除",
    "AssignUnauthorized": "您沒有指派此角色所需之權限",
    "UnassignUnauthorized": "您沒有移除指派此角色所需之權限",
    "UpdateUnauthorized": "您沒有修改此角色所需之權限",
    "DeleteUnauthorized": "您沒有移除此角色所需之權限",
    "AddRole": "添加角色"
  },
  "Claims": {
    "Title": "宣告",
    "New": "新增宣告類型",
    "ClaimTypeName": "宣告類型名稱",
    "ClaimTypeDescription": "宣告描述",
    "ClaimTypeRule": "宣告類型規則",
    "RegexRule": "正規表示式規則",
    "RuleValidationFailureDescription": "規則驗證失敗說明",
    "Required": "必填之宣告",
    "FutureUsers": "未來新增使用者時必須有值",
    "AddAnother": "選擇 <strong>新增另一項宣告</strong> 在提交後繼續保留此對話框，您可以繼續新增另一項宣告.",
    "DeleteConfirmation": "你是否要刪除此宣告類型",
    "Search": "搜尋宣告名稱...",
    "UserEditable": "如果通過對外公開的顯露，則使用者可以編輯這些值",
    "AssignUnassignUnauthorized": "您沒有指派或移除指派此宣告(Claim)所需之權限",
    "NoClaimsFound": "未找到任何宣告",
    "Add": "添加声明类型",
    "AddAnotherClaimType": "送出後新增其他聲明類型"
  },
  "Resources": {
    "ResourceID": "資源ID",
    "ResourceStatus": "資源狀態",
    "RemovedResource": "移除資源",
    "RemovedResourceScope": "移除資源範圍",
    "EnterBasicDetails": "請輸入以下基本項目",
    "DescriptionHelp": "在同意畫面出現的資源描述",
    "ResourceAddedSuccess": "新增資源成功",
    "AssignClaims": "指派將包含在Tokens中之使用者宣告",
    "UniqueIdentifier": "此資源的識別ID",
    "ResourceName": "在Admin UI中使用的資源名稱",
    "ResourceDescription": "在Admin UI中使用的資源描述",
    "UpdatedSuccess": "更新資源成功",
    "AddResource": "添加资源",
    "Scope": {
      "NewScope": "新範圍",
      "DisplayName": "在同意畫面出現之範圍名稱",
      "Description": "在同意畫面出現之範圍描述",
      "ScopeFor": "scope for the",
      "Updated": "更新範圍成功",
      "Failed": "更新範圍失敗",
      "ScopeID": "範圍ID",
      "Consent": "需要同意使用範圍才能完成身份驗證",
      "DiscoveryDocumentDescription": "範圍顯示於探索文件 (<em>/.well-known/openid-configuration</em>)",
      "EmphasiseScope": "在同意畫面上強調範圍名稱",
      "UserClaimTypes": "Tokens內包含使用者宣告類型，宣告類型將被附加到上層資源的宣告類型列表中.",
      "ScopeAdded": "範圍已新增"
    }
  },
  "IdentityResources": {
    "Title": "身份資源",
    "Singular": "身份資源",
    "Create": "建立身份資源",
    "UserClaimTypes": "指派Tokens中包含之使用者宣告類型",
    "IDHelp": "用於請求時此資源的唯一識別ID",
    "DisplayNameHelp": "在同意畫面出現的資源名稱",
    "ConsentResource": "需要同意使用資源才能完成身份驗證",
    "DiscoveryDocumentDescription": "資源顯示於探索文件 (<em>/.well-known/openid-configuration</em>)",
    "ShowInDiscoveryDocument": "顯示於探索文件",
    "ConsentScreen": "在同意畫面上強調資源名稱",
    "UpdatedClient": "更新用戶端成功",
    "ResourceReservedHelp": "此項應用程式介面資源被設定為保留項目，不可修改",
    "NoIdentityResources": "找不到身份資源",
    "Reserved": "此為保留項目，不可修改"
  },
  "ProtectedResources": {
    "Title": "應用程式介面資源",
    "TitlePlural": "應用程式介面資源",
    "Create": "建立應用程式介面資源",
    "AssignClaims": "指定要包含在Token內的使用者宣告類型",
    "Secrets": "輸入密鑰 (非必填)",
    "UserClaimTypes": "包含在Token中的使用者宣告類型。 適用於所有範圍的資源.",
    "AddScope": "新增範圍",
    "ProtectedResource": "應用程式介面資源?",
    "ClientAccess": "選擇此用戶端可以存取之應用程式介面資源",
    "NoneFound": "找不到應用程式介面資源"
  },
  "Clients": {
    "Export": {
      "ExportAll": "匯出全部",
      "ExportAllClients": "匯出所有客戶",
      "ExportSelected": "匯出所選",
      "ExportSelectedClients": "匯出選定的客戶"
    },
    "Import": {
      "Import": "匯入",
      "ImportClients": "匯入客戶",
      "Wizard": {
        "Setup": {
          "Title": "匯入客戶",
          "Summary": "從另一個AdminUI解決方案匯入客戶及資源。",
          "ChooseFile": "選擇檔案",
          "ChooseFileHelp": "從另一個AdminUI解決方案匯出的JSON文件",
          "CheckImportPleaseWait": "驗證中，請稍候",
          "Errors": {
            "Default": "很抱歉，匯入時出現問題。請再試一次。",
            "InvalidFile": "抱歉，讀取文件時出現問題。請再試一次。",
            "InvalidData": "很抱歉，文件資料無效。請檢視並再試一次。",
            "CompleteImportFailed": "很抱歉，匯入期間出現錯誤。請再試一次。"
          }
        },
        "Secrets": {
          "Title": "密碼",
          "ChooseWhatToDo": "請選擇要如何處理先前建立的機密。",
          "DoNotSet": "不要設定密碼",
          "Generate": "製作隨機密碼",
          "ManuallyCreate": "手動建立密碼",
          "RememberMyDecision": "記住設定並套用到所有目前的密碼",
          "UseExistingSecrets": "使用現有的密碼",
          "Note": {
            "Note": "匯入後即可下載新密碼",
            "Title": "備註"
          },
          "ProtectedResource": "受保護的資源",
          "IdentityResource": "身份資源",
          "Client": "客戶",
          "ClaimType": "宣告類型"
        },
        "Certificates": {
          "Title": "憑證",
          "ChooseWhatToDo": "請選擇如何處理先前連結的憑證。",
          "DoNotSet": "不新增憑證",
          "UploadNewCertificates": "上載新憑證",
          "RememberMyDecision": "記住設定並套用到所有目前的憑證",
          "UseExistingCertificates": "使用現有的憑證",
          "AddCertificate": "新增憑證",
          "FailedToParseCertificate": "解析憑證失敗",
          "TryAgainDifferentFile": "請使用其他憑證再試一次",
          "DuplicateCertificate": "憑證已新增",
          "InvalidCertificate": "憑證重複"
        },
        "Warning": {
          "Title": "警告",
          "Text1": "客戶尚未匯入完成。",
          "Text2": "確定要離開嗎?",
          "DownloadSecrets": "新密碼已製作。",
          "Yes": "是",
          "No": "否"
        },
        "Summary": {
          "LinkedClients": "哪些客戶與這資源相依？",
          "EffectsImportClients": "匯入",
          "EffectsExistingClients": "現有的",
          "NewClients": "新客戶",
          "ExistingClients": "現有客戶",
          "ClientsHelp": "匯入資源會影響的客戶數量",
          "DependencyConflicts": "相依",
          "Title": {
            "All": "匯入摘要",
            "Client": "客戶總結",
            "Resource": "資源彙整",
            "ClaimType": "宣告類型摘要",
            "Final": "最終匯入摘要"
          },
          "Name": {
            "Client": "客戶名稱",
            "Resource": "資源名稱",
            "ClaimType": "宣告類型"
          },
          "Identifier": {
            "Client": "客戶 ID",
            "Resource": "資源ID",
            "ClaimType": "宣告類型"
          },
          "Type": {
            "Client": "客戶類型",
            "Resource": "資源類型",
            "ClaimType": "數值類型"
          },
          "Intro": {
            "Client": "請選擇要匯入的客戶。",
            "Resource": "匯入期間將更新以下資源。",
            "ClaimType": "匯入期間將更新以下宣告類型。"
          },
          "ClientName": "客戶名稱",
          "ClientId": "客戶 ID",
          "ClientType": "客戶類型",
          "Change": "變更",
          "Changes": "變更",
          "Conflicts": {
            "ReviewChanges": "檢視變更",
            "ConflictedServiceProvider": "服務廠商衝突",
            "ConflictedRelyingParty": "信賴憑證者衝突",
            "ConflictedScopes": "衝突範圍",
            "ConfirmationText": {
              "Client": "匯入這個客戶會變更以下內容。請問要接受變更嗎？",
              "Resource": "匯入這個資源會變更以下內容。請問要接受變更嗎？",
              "ClaimType": "匯入這個宣告會變更以下內容。請問要接受變更嗎？"
            },
            "Property": "屬性",
            "Key": "金鑰",
            "OldValue": "目前的數值",
            "NewValue": "新的數值",
            "NoValue": "沒有數值",
            "Deleted": "已刪除",
            "Accept": "接受",
            "Decline": "拒絕",
            "Cancel": "取消",
            "Confirmation": {
              "AreYouSure": "確定不要匯入變更嗎",
              "Client": "這個客戶將不會匯入",
              "Resource": "所有連結的客戶都從這次匯入中刪除"
            }
          },
          "ResourceTypes": {
            "Unknown": "未知",
            "ServerSide": "網頁應用程式",
            "Machine": "機器",
            "Native": "原生",
            "Device": "載具",
            "Saml": "服務廠商",
            "WsFed": "WS-Fed信賴憑證者",
            "BrowserBased": "單一頁面",
            "LegacyClientSide": "單頁應用程式（舊版）",
            "Identity": "身分識別",
            "Protected": "受保護",
            "String": "字串",
            "Int": "Int",
            "DateTime": "日期時間",
            "Boolean": "布林值"
          },
          "FinalSummary": "檢視要匯入的客戶和資源。重複項將不會匯入。"
        },
        "CompleteImport": {
          "ImportInProgress": "匯入中...",
          "ImportComplete": "匯入完成",
          "ImportSuccess": "選定的客戶及有關資源已成功匯入",
          "ImportSuccessMultiple": "{0}個客戶及有關資源已成功匯入",
          "ImportFailure": "匯入失敗",
          "FinishImport": "完成",
          "DownloadSecrets": "下載密碼"
        }
      }
    },
    "ID": "用戶端ID",
    "Title": "用戶端",
    "Add": "新增用戶端",
    "EnterBasicDetails": "請輸入下列基本項目",
    "IDHelp": "此應用程式的識別ID(請使用CLI0000001格式編碼)",
    "Secrets": "輸入密鑰",
    "Review": "在提交前的最後檢查",
    "DisplayNameHelp": "在同意畫面出現的應用程式名稱",
    "DisplayURLHelp": "在同意畫面出現的應用程式 URL",
    "LogoURLHelp": "在同意畫面出現的應用程式Logo圖示位置. 必須使用HTTPS.",
    "DescriptionHelp": "Admin UI的應用程式描述",
    "RedirectURLDescription": "導回網址的完整路徑. 在正式環境時請務必設定為HTTPS",
    "LogoutURLDescription": "登出時使用者將被重導之網址. 於正式環境時請務必設定為HTTPS",
    "IdentityResourcesAccess": "選擇此用戶端可存取之身份資源(Identity Resource)",
    "ProtectedResourcesAccess": "選擇此用戶端可存取之應用程式介面資源(Api Resource)",
    "Setup": "設定用戶端應用程式精靈",
    "SelectType": "請選擇一種您想要建立的應用程式種類",
    "StaticClaims": "此用戶端應用程式之Access Token中回傳靜態宣告. 預設情況下，這些宣告僅與用戶端證書(Client Credentials)授權類型一起發送.",
    "AllowClaims": "允許用戶端宣告傳送至所有授權類型",
    "SendClaims": "總是傳送宣告",
    "PrefixClaims": "選擇您想用的前置宣告文字",
    "PrefixClaimsTitle": "前置宣告",
    "Restrictions": "限制Client可以使用的身份提供者(IdP,例如Google、Facebook或目前已支援之其他IdP，或是啟用本地登入)。未設定則允許所有登入方式。",
    "AddRestriction": "新增限制",
    "ProviderName": "識別提供者(IdP)名稱",
    "Delete": "刪除用戶端",
    "AddedSecret": "新增密鑰成功",
    "UnableToAddSecret": "無法新增密鑰",
    "UnableToAddProperty": "無法新增屬性，關鍵值已存在",
    "RemovedSecret": "移除密鑰成功",
    "UnableToRemoveSecret": "無法移除密鑰",
    "UpdatedClient": "更新用戶端成功",
    "Deleted": "用戶端已刪除",
    "Search": "搜尋用戶端...",
    "Reserved": "此為保留項目，不可修改",
    "None": "找不到用戶端",
    "NoSecrets": "尚未設置密鑰。請利用上方的表單新增，產出之密鑰將顯示於此.",
    "EnableLocalLogin": "啟用本地登入",
    "CORSUrl": "此Url是一個路徑，不能作為CORS Url",
    "NullURL": "URL為空白",
    "UrlIsPath": "此Url是一個路徑，不能作為CORS Url",
    "UrlNotValid": "此Url不正確",
    "EntityId": "實體識別碼",
    "Realm": "領域",
    "Created": "已建立",
    "CallbackURL": "輸入回撥URL<br/><small>權杖會傳送至此端點(您可以等到安裝後再設定更多內容)</small> ",
    "PostLogoutURL": "輸入登出後輸入URL<br /><small>可省略(您可以等到安裝後再設定更多內容)</small> ",
    "NoClaims": "找不到任何用戶端角色",
    "NoRestrictions": "找不到任何用戶端限制",
    "DuplicateProvider": "已新增提供者",
    "NoCertificates": "找不到憑證",
    "RelyingParty": {
      "Heading": "信賴憑證者",
      "General": "一般",
      "TokenType": "權杖類型",
      "SignatureAlgorithm": "簽章演算法",
      "DigestAlgorithm": "摘要演算法",
      "SAMLNameIdFormat": "SAML Name Id Format"
    },
    "ClaimMappings": {
      "Heading": "宣告對應",
      "ClaimType": "宣告類型",
      "AssertionType": "判斷提示類型",
      "None": "找不到任何宣告對應",
      "AssertionTypeHeading": "宣告類型對應",
      "AssertionTypeHeadingHelp": "新增宣告類型對應，或新增您自己的",
      "AssertionTypeAlias": "別名",
      "AssertionTypeValue": "數值",
      "AssertionTypeSearch": "搜尋知名的宣告類型對應",
      "ExisitingMappingWarning": "宣告類型已對應：",
      "UseDefaults": "刪除宣告對應並使用預設",
      "DeleteAll": "全部刪除",
      "DeleteAllWarning": "這將刪除所有目前的宣告對應。確定嗎？",
      "AssertionTypeValues": {
        "Actor": "動作項目",
        "Anonymous": "匿名",
        "Authentication": "驗證",
        "AuthenticationInstant": "即時驗證",
        "AuthenticationMethod": "驗證方法",
        "AuthorizationDecision": "授權決策",
        "CookiePath": "Cookie路徑",
        "Country": "國家",
        "DateOfBirth": "出生日期",
        "DenyOnlyPrimaryGroupSid": "僅限拒絕主要群組SID",
        "DenyOnlyPrimarySid": "僅限拒絕主要SID",
        "DenyOnlySid": "僅限拒絕SID",
        "DenyOnlyWindowsDeviceGroup": "僅限拒絕Windows裝置群組",
        "Dns": "DNS",
        "Dsa": "DSA",
        "Email": "電子郵件",
        "Expiration": "逾期",
        "Expired": "過期",
        "Gender": "性別",
        "GivenName": "指定名稱",
        "GroupSid": "群組SID",
        "Hash": "雜湊",
        "HomePhone": "住家電話",
        "IsPersistent": "持續發生",
        "Locality": "位置",
        "MobilePhone": "行動電話",
        "Name": "名稱",
        "NameIdentifier": "名稱識別碼",
        "OtherPhone": "其他電話",
        "PostalCode": "郵遞區號",
        "PrimaryGroupSid": "主要群組SID",
        "PrimarySid": "主要SID",
        "Role": "角色",
        "Rsa": "RSA",
        "SerialNumber": "序號",
        "Sid": "SID",
        "Spn": "服務主體名稱",
        "StateOrProvince": "省份",
        "StreetAddress": "街道地址",
        "Surname": "姓氏",
        "System": "系統",
        "Thumbprint": "憑證指紋",
        "Upn": "UPN",
        "Uri": "URI",
        "UserData": "使用者資料",
        "Version": "版本",
        "Webpage": "網頁",
        "WindowsAccountName": "Windows帳戶名稱",
        "WindowsDeviceClaim": "Windows裝置宣告",
        "WindowsDeviceGroup": "Windows裝置群組",
        "WindowsFqbnVersion": "Windows FQBN版本",
        "WindowsSubAuthority": "Windows子授權",
        "WindowsUserClaim": "Windows使用者宣告",
        "X500DistinguishedName": "X500 Distinguished Name"
      }
    },
    "GrantTypes": {
      "Implicit": "隱含(implicit)",
      "AuthCode": "授權碼(authorization_code)",
      "Hybrid": "混合(hybrid)",
      "Password": "密碼(password)",
      "Custom": "客製化",
      "ClientCredentials": "用戶端憑證(client_credentials)",
      "DeviceFlow": "裝置流",
      "None": "No grant types found"
    },
    "Properties": {
      "None": "No properties found"
    },
    "RequireConsent": {
      "Title": "需要使用者同意",
      "Help": "指定是否需要使用者同意畫面",
      "Summary": "Require Consent"
    },
    "AllowRememberConsent": {
      "Title": "記住使用者同意",
      "Help": "指定是否記住使用者同意畫面記錄"
    },
    "RequireSecret": {
      "Title": "需要密鑰?",
      "Help": "指定是否需要密鑰"
    },
    "Tokens": {
      "RequirePkce": "需要PKCE",
      "AccessTokensViaBrowser": "允許存取權杖，以便透過瀏覽器傳送",
      "AccessTokensViaBrowserSummary": "停用對強化流程而言相當好用，允許多重授與類型。",
      "Title": "Tokens",
      "ClientTokenLifetime": "Identity Token 生命週期 (秒)",
      "AccessTokenLifetime": "Access Token 生命週期 (秒)",
      "ConsentLifetime": "Consent Token 生命週期 (秒)",
      "FrontChannelLogoutUri": "前端通道登出網址",
      "PairWiseSubjectSalt": "成對 Subject Salt",
      "FrontChannelLogoutSessionRequired": "需要前端通道登出Session",
      "AuthTokenLifetime": "Authorization Token 生命週期 (秒)",
      "RefreshTokenLifetime": "絕對 Refresh Token 生命週期 (秒)",
      "AccessTokenType": "Access Token 類型",
      "Jwt": "Jwt",
      "Reference": "Reference",
      "Refresh": "Refresh Token 用法",
      "OneTime": "一次性",
      "ReUse": "重覆使用",
      "Expiration": "Refresh Token 逾期",
      "Absolute": "絕對",
      "SlidingRefreshTokenLifetime": "Sliding Token 逾期",
      "Sliding": "滑動",
      "AllowPlainTextPkce": "允許純文字 Pkce",
      "AllowOfflineAccess": "允許離線存取",
      "UpdateAccessTokensSummary": "當使用Refresh Token時，更新Access Tokens (及其宣告)",
      "UpdateAccessTokens": "當刷新時更新 Access Token 宣告",
      "IncludeJwtId": "包含 Jwt Id",
      "LogoutSessionRequired": "要求Seesion觸發登出",
      "IncludeUserClaimsInIdToken": "Id Token中包含使用者宣告",
      "BackChannelLogoutSessionRequired": "需要後端登出Session",
      "BackChannelLogoutUri": "後端登出URI",
      "UserSSOLifetime": "SSO存留期(秒)",
      "UserSSOLifetimeTooltip": "驗證挑戰之間的時間量。默認為IdentityServer工作階段存留期",
      "UserCode": "使用者代碼生成器類型",
      "DeviceCodeLifetime": "裝置流請求存留期",
      "DurationTitle": "計算存留期時長",
      "Durations": {
        "Seconds": "秒",
        "SecondsShort": "s",
        "Second": "秒",
        "SecondShort": "s",
        "Minutes": "分",
        "MinutesShort": "mins",
        "Minute": "分",
        "MinuteShort": "min",
        "Hours": "小時",
        "HoursShort": "hrs",
        "Hour": "小時",
        "HourShort": "hr",
        "Days": "天",
        "DaysShort": "d",
        "Day": "天",
        "DayShort": "d",
        "Weeks": "星期",
        "WeeksShort": "wk",
        "Week": "星期",
        "WeekShort": "wk",
        "Months": "月",
        "MonthsShort": "mos",
        "Month": "月",
        "MonthShort": "mo",
        "Years": "年",
        "YearsShort": "yrs",
        "Year": "年",
        "YearShort": "yr",
        "Unlimited": "無限",
        "UnlimitedShort": "∞"
      }
    },
    "Home": {
      "Title": "設定用戶端應用程式",
      "Description": "從清單中選擇應用程式類型，深入了解。<br />然後按一下 \"開始\"開始安裝程式。"
    },
    "WizardTypes": {
      "WebAppSelection": "選擇支援的流程",
      "WebApplication": "混合式流程及用戶端驗證",
      "PKCEWebApplication": "授權碼流程+PKCE"
    },
    "MachineToMachine": {
      "Setup": "設定伺服器應用程式",
      "Title": "伺服器",
      "Created": "伺服器應用程式已建立",
      "Summary": "用戶端認證",
      "Description": "機器對機器的通訊模式。<br />過程中沒有使用者涉入。<br />會透過反向通道通訊來傳送權杖。"
    },
    "SPA": {
      "Setup": "設定SPA應用程式",
      "Title": "單頁式網頁",
      "Created": "SPA應用程式已建立",
      "ExtractedDomain": "從您的網域中提取",
      "Summary": "授權碼流程+PKCE",
      "Description": "用戶端應用程式在瀏覽器中運作。以上應用程式基本上無法保密，卻可以使用重<br/>新整理權杖。<br/>會透過瀏覽器傳送權杖，就能讓使用者看見。"
    },
    "LegacySPA": {
      "Setup": "設定舊版單一頁面應用程式",
      "Title": "單一頁面應用程式(舊版)",
      "Summary": "隱含流程",
      "Description": "使用之前的OAuth工作小組建議，用戶端應用程式就能在瀏覽器中運作。<br/>以上應用程式無法保密，卻可以使用重新整理權杖。<br/>會透過瀏覽器傳送權杖，就能讓使用者看見。",
      "Created": "舊版單一頁面應用程式已建立",
      "ExtractedDomain": "Extracted from your domain"
    },
    "WebApp": {
      "Setup": "設定Web應用程式",
      "Created": "Web 應用程式已建立",
      "Title": "Web應用程式",
      "Summary": "混合式流程及用戶端驗證",
      "Description": "伺服器端應用程式可在基礎結構中運作。<br />以上應用程式無法保密，卻可以使用重新整理權杖。<br/>會透過瀏覽器傳送權杖，就能讓使用者看見。",
      "Secrets": "輸入部分秘密（選填）"
    },
    "PKCEWebApp": {
      "Setup": "設定網路應用程式",
      "Title": "網路應用程式",
      "Summary": "授權碼流程+PKCE",
      "Description": "伺服器端應用程式可在基礎結構中運作。<br />以上應用程式無法保密，卻可以使用重新整理權杖。<br/>會透過瀏覽器傳送權杖，就能讓使用者看見。",
      "Created": "已建立網路應用程式",
      "Secrets": "輸入部分秘密（選填）"
    },
    "NativeApp": {
      "Setup": "設定原生應用程式",
      "Title": "原生",
      "Created": "原生應用程式已建立",
      "Summary": "授權碼流程+PKCE",
      "Description": "桌面或行動應用程式可在使用者裝置中運作。<br />以上應用程式無法保密，卻可以使用重新整理權杖。<br />權杖可見度與瀏覽器和重新導向URI選擇有關。",
      "Secrets": "輸入部分秘密（選填）"
    },
    "DeviceFlow": {
      "Setup": "設定裝置",
      "Created": "裝置流應用程式已建立",
      "Title": "裝置",
      "Summary": "裝置流量使用到外部瀏覽器",
      "Description": "IoT應用程式或否則不需瀏覽器的限制輸入裝置。<br />以上應用程式基本上無法保密，卻可以使用重新整理權杖。"
    },
    "Saml": {
      "Setup": "設定SAML服務提供者",
      "Title": "SAML服務提供者",
      "Summary": "SAML 2.0應用程式",
      "Description": "SAML 2.0服務提供者常用於政府和教育機構。<br />無法用於API存取。",
      "Created": "SAML服務提供者已建立",
      "DefaultEndpoint": "預設端點",
      "LocationUrl": "位置網址",
      "LocationNotValid": "位置無效",
      "BindingType": "繫結類型",
      "Index": "索引",
      "IndexNotUnique": "索引必須是唯一的",
      "ACSEndpoints": "存取控制服務端點",
      "SLOEndpoints": "SLO端點",
      "NoEndpoints": "<strong>沒有端點安裝程式</strong>",
      "Response": "回應",
      "LocationBindingUnique": "端點和繫結類型必須是唯一的",
      "Request": "請求",
      "RequireRequestDestination": "需要請求目的地",
      "RequireRequestDestinationHelp": "確定傳入的SAML請求包含目的地值，允許IdentityServer確認這是預定的收件者(建議使用)",
      "SignAssertions": "簽署宣告",
      "SignAssertionsHelp": "讓IdentityServer同時簽署SAML訊息和宣告(建議使用)",
      "EncryptAssertions": "加密宣告",
      "EncryptAssertionsHelp": "將使用到公開金鑰的IdentityServer加密宣告傳送給服務提供者",
      "AddCert": "新增憑證",
      "DeleteCert": "刪除憑證",
      "AddCertSummary": "上傳憑證或將憑證值貼到中繼資料",
      "AddCertNote": "儲存時將會立即套用憑證",
      "UploadCert": "上傳憑證",
      "UploadCertHelp": "上傳有效的.cer檔案",
      "UploadCertViaMetadata": "透過中繼資料來上傳",
      "ServiceProviderSigningCert": "服務提供者簽署憑證",
      "ServiceProviderSigningCertHelp": "服務提供者公開金鑰的X509憑證值",
      "CertUploadSuccess": "憑證上傳成功",
      "InvalidCert": "憑證無效",
      "DuplicateCert": "複製憑證",
      "DuplicateCertMessage": "此憑證已存在於服務提供者中",
      "IndexInvalidType": "索引應為數字",
      "ReplaceCertificate": "替換憑證",
      "CannotDeleteResponseCert": "Cannot delete encryption certificate while encrypt assertions is true",
      "AllowIdpInitiatedSso": "允許 IdP 初始化的單一登入",
      "AllowIdpInitiatedSsoHelp": "透過識別提供者，允許單一登入初始化（不建議）"
    },
    "WsFed": {
      "Setup": "設定WS-同盟信賴憑證者",
      "Title": "WS-Fed信賴憑證者",
      "Summary": "WS-Federation應用程式",
      "Description": "WS-Federation信賴憑證者常用於較舊的Microsoft應用程式。<br />無法用於API存取。",
      "Created": "WS-Federation Relying Party Created"
    },
    "URLS": {
      "Title": "應用程式 URLs",
      "SendTokens": "可傳送Tokens至此URL",
      "RedirectAfterLogout": "登出後將重導至此URL",
      "CORSDomain": "此網域會造成跨網域請求",
      "NoURLS": "不可缺少重導之urls",
      "URLAddUnsuccessful": "增加URL時發生問題",
      "None": "找不到應用程式URL"
    },
    "Selected": "(已選取)",
    "Endpoint": "端點",
    "Redirect": "重新導向",
    "Post": "張貼",
    "AcsEndpoints": "存取控制服務端點",
    "AcsEndpointHelp": "存取控制服務端點網址 以上通訊協定以上仰賴生產中的TLS",
    "SloEndpoints": "SLO端點",
    "SloEndpointHelp": "SLO端點網址 以上通訊協定以上仰賴生產中的TLS",
    "BindingType": "繫結類型",
    "BindingTypeHelp": "指定端點的繫結類型",
    "IndexHelp": "Index of the endpoint"
  },
  "Secret Picker": {
    "Set Expiration Button": "(非必填)過期時間設定",
    "HiddenValue": "值已被隱藏",
    "LastWarning": "警告：建立內容之後，就無法存取秘密值"
  },
  "Notifications": {
    "Success": "成功",
    "Failure": "失敗",
    "Failed": "失效",
    "Sorry": "很抱歉",
    "Delete Error Title": "刪除錯誤",
    "Delete User Message": "刪除使用者發生問題",
    "Saving Error Title": "儲存錯誤",
    "Saving Error Message": "儲存變更發生問題",
    "Saving Success Title": "成功",
    "Saving Success Message": "變更已儲存",
    "SuccessfullyCreated": "建立成功",
    "UsernameTaken": "使用者名稱已被使用",
    "AccountCreated": "帳號已建立",
    "AllAppsRevoked": "所有應用程式已成功撤消",
    "AppRevoked": "應用程式已成功撤消",
    "UnsavedChanges": "您尚未儲存變更",
    "SomethingWrong": "發生一些問題",
    "CheckLogs": "請檢查日誌.",
    "Apology": "由於系統崩潰，我們將回到主頁面",
    "Support": "留訊息至support@identityserver.com尋求更多協助",
    "Reset Success Message": "密碼重設成功",
    "Reset Error Message": "使用者密碼重設發生問題",
    "Error": "錯誤",
    "Unauthorized": "未授權",
    "UnsavedChangesTitle": "未儲存的變更",
    "ContinueWithoutSaving": "確定不儲存就離開瀏覽嗎？",
    "DiscardChanges": "捨棄變更",
    "StayHere": "停留在本頁",
    "Notice": "注意",
    "DontForgetToSave": "別忘了儲存變更"
  },
  "Settings": {
    "Title": "設定/存取原則",
    "AccessPolicy": {
      "ClaimType": "宣告類型",
      "ClaimValue": "宣告值",
      "Permission": "權限",
      "Save": "存檔",
      "ConfirmSave": "您確定要變更這些存取原則嗎?",
      "ConfirmChanges": "確認存取原則變更",
      "SaveYes": "變更存檔",
      "SaveNo": "不要存檔",
      "InvalidClaimType": "未選擇宣告類型",
      "InvalidClaimValue": "未輸入宣告值",
      "InvalidPermission": "未選擇權限",
      "AccessPolicyUpdated": "存取原則已變更",
      "AccessPolicyConflict": "衝突：存取原則已存在",
      "Title": "設定/存取原則",
      "Add": "新增原則",
      "NewPolicy": "新存取原則"
    }
  },
  "LandingPage": {
    "Welcome": "Welcome to",
    "LatestNews": "最新消息",
    "IntroParagraph1": "IdentityServer4 領先的使用者與組態管理工具",
    "IntroParagraph2": "如需授權諮詢,請聯繫:",
    "Documentation": "說明文件(英文)",
    "APIDocs": "API 文件(Swagger)",
    "IdentityServerError": "無法連線IdentityServer",
    "APIError": "無法連線API"
  },
  "Permission": {
    "UserManager": "使用者管理員",
    "IdentityServerManager": "IdentityServer管理員",
    "All": "全部",
    "Auditer": "審計員"
  },
  "Auditing": {
    "ToggleDetails": "切換詳情",
    "Title": "正在審計",
    "SearchAudits": "搜尋審計",
    "NoAuditsFound": "未找到審計",
    "When": "時間",
    "Subject": "主題",
    "Resource": "資源",
    "Source": "來源",
    "Action": "操作",
    "Description": "描述",
    "Succeeded": "成功",
    "FromDate": "起始日期",
    "ToDate": "結束日期",
    "SetDateToday": "將日期設定為今天",
    "Today": "今天",
    "SetDateLast24Hours": "設定最近24小時的日期",
    "24Hours": "24小時",
    "SetDateYesterday": "將日期設定為昨天",
    "Yesterday": "昨天",
    "SetDateLastWeek": "將日期設定為星期",
    "Week": "星期",
    "ResultsPerPage": "每頁結果數",
    "AddFilter": "新增篩選器",
    "ShowFilters": "顯示篩選器",
    "HideFilters": "隱藏篩選器",
    "FilterTerm": "篩選詞",
    "FilterTermPlaceholder": "篩選詞...",
    "RemoveFilter": "刪除篩選器",
    "Showing": "顯示",
    "ExecuteAndDownload": "執行並下載",
    "ExecuteAndDisplay": "更新結果",
    "UpdateWarning": "按一下「更新結果」以查看您的更改",
    "Reset": "重設",
    "Result": "結果",
    "First page of results": "結果第一頁",
    "Previous page of results": "結果的上一頁",
    "Next page of results": "結果的下一頁",
    "Last page of results": "結果的最後一頁",
    "DownloadResults": "匯出",
    "FromDateWarning": "開始日期不能是未來的時間",
    "ToDateBehindWarning": "結束日期不能早於開始日期",
    "ActiveFilters": "使用中的篩選",
    "AddFilterTerm": "新增篩選條件"
  },
  "Resource": {
    "user": "使用者",
    "role": "角色",
    "claimType": "ClaimType",
    "client": "用戶端",
    "identityResource": "識別資源",
    "protectedResource": "受保護資源",
    "serviceProvider": "服務提供者",
    "relyingParty": "信賴憑證者"
  }
}